setup.py
telecom_invoice/__init__.py
telecom_invoice/constants.py
telecom_invoice/fields.py
telecom_invoice/models.py
telecom_invoice.egg-info/PKG-INFO
telecom_invoice.egg-info/SOURCES.txt
telecom_invoice.egg-info/dependency_links.txt
telecom_invoice.egg-info/requires.txt
telecom_invoice.egg-info/top_level.txt
test/__init__.py
test/test_item.py
test/test_master.py
test/test_register.py