Metadata-Version: 1.1
Name: telecom-invoice
Version: 0.0.1
Summary: Gerador de arquivos serializados das NFs de Serviços em Telecomunicação
Home-page: UNKNOWN
Author: Matheus Marchini
Author-email: matheus@sthima.com.br
License: MIT
Keywords: invoice brazil brasil telecom
Platform: UNKNOWN
Classifier: Development Status :: 3 - Alpha
Classifier: Intended Audience :: Developers
Classifier: License :: OSI Approved :: MIT License
Classifier: Programming Language :: Python :: 2
Classifier: Programming Language :: Python :: 2.7
